ghscard/__init__.py
ghscard/__main__.py
ghscard/__version__.py
ghscard/_cache.py
ghscard/_const.py
ghscard/_detector.py
ghscard/_emoji.py
ghscard/_error.py
ghscard/_generator.py
ghscard/_github_client.py
ghscard/_logger.py
ghscard/_stopwatch.py
ghscard/fetcher/__init__.py
ghscard/fetcher/_base.py
ghscard/fetcher/_common.py
ghscard/fetcher/_organization.py
ghscard/fetcher/_repository.py
ghscard/fetcher/_user.py
ghscard-0.5.3.dist-info/LICENSE
ghscard-0.5.3.dist-info/METADATA
ghscard-0.5.3.dist-info/WHEEL
ghscard-0.5.3.dist-info/entry_points.txt
ghscard-0.5.3.dist-info/top_level.txt
ghscard-0.5.3.dist-info/RECORD
