Metadata-Version: 2.1
Name: ghscard
Version: 0.5.3
Summary: ghscard is a JavaScript widget to generate interactive GitHub user/repository/organization cards for static web pages (like GitHub pages/Read the Docs).
Home-page: https://github.com/thombashi/ghscard
Author: Tsuyoshi Hombashi
Author-email: tsuyoshi.hombashi@gmail.com
License: MIT License
Project-URL: Documentation, https://ghscard.rtfd.io/
Project-URL: Source, https://github.com/thombashi/ghscard
Project-URL: Tracker, https://github.com/thombashi/ghscard/issues
Keywords: GitHub,JavaScript,Widget
Platform: UNKNOWN
Classifier: Development Status :: 4 - Beta
Classifier: Intended Audience :: Developers
Classifier: Intended Audience :: Information Technology
Classifier: License :: OSI Approved :: MIT License
Classifier: Operating System :: OS Independent
Classifier: Programming Language :: JavaScript
Classifier: Programming Language :: Python :: 3
Classifier: Programming Language :: Python :: 3.5
Classifier: Programming Language :: Python :: 3.6
Classifier: Programming Language :: Python :: 3.7
Classifier: Programming Language :: Python :: 3.8
Classifier: Topic :: Software Development
Classifier: Topic :: Software Development :: Widget Sets
Requires-Python: >=3.5
Requires-Dist: setuptools (>=38.3.0)
Requires-Dist: appconfigpy (<2,>=1.0.1)
Requires-Dist: click (<8,>=6.2)
Requires-Dist: colorama (<1,>=0.3.7)
Requires-Dist: Logbook (<2,>=0.12.3)
Requires-Dist: DateTimeRange (<2,>=1.0.0)
Requires-Dist: msgfy (<1,>=0.1.0)
Requires-Dist: path (<16,>=13.0.0)
Requires-Dist: pathvalidate (<3,>=2.2.2)
Requires-Dist: PyGithub (<2,>=1.43.7)
Requires-Dist: retryrequests (<1,>=0.0.2)
Requires-Dist: typepy (<2,>=1.1.1)
Requires-Dist: typing-extensions (>=3.7.4)
Provides-Extra: test
Requires-Dist: pytest ; extra == 'test'
Requires-Dist: pytest-md-report ; extra == 'test'
